{
  "id": "9f27b198-c959-1ce3-1a8b-ecfcc29873a1",
  "name": "noneoftheabove-localhost-postman-environment",
  "values": [
    {
      "enabled": true,
      "key": "server",
      "value": "localhost:3001",
      "type": "text"
    },
    {
      "enabled": true,
      "key": "protocol",
      "value": "http",
      "type": "text"
    },
    {
      "enabled": true,
      "key": "electionAdminId",
      "value": "electionAdmin-1",
      "type": "text"
    },
    {
      "enabled": true,
      "key": "organizationId",
      "value": "org-1",
      "type": "text"
    },
    {
      "enabled": true,
      "key": "referendumId",
      "value": "ref-1",
      "type": "text"
    },
    {
      "enabled": true,
      "key": "referendumId2",
      "value": "ref-2",
      "type": "text"
    },
    {
      "enabled": false,
      "key": "voterId",
      "value": "{{$guid}}",
      "type": "text"
    }
  ],
  "timestamp": 1495625339672,
  "_postman_variable_scope": "environment",
  "_postman_exported_at": "2017-05-24T11:29:07.835Z",
  "_postman_exported_using": "Postman/4.10.7"
}